pdf_parse_bench/__init__.py
pdf_parse_bench/eval/__init__.py
pdf_parse_bench/eval/evaluators.py
pdf_parse_bench/extraction/__init__.py
pdf_parse_bench/extraction/segment_extractor.py
pdf_parse_bench/pipeline/__init__.py
pdf_parse_bench/pipeline/cli.py
pdf_parse_bench/pipeline/pipeline.py
pdf_parse_bench/synth_pdf/__init__.py
pdf_parse_bench/synth_pdf/__main__.py
pdf_parse_bench/synth_pdf/content.py
pdf_parse_bench/synth_pdf/latex.py
pdf_parse_bench/synth_pdf/latex_config.py
pdf_parse_bench/synth_pdf/pipeline.py
pdf_parse_bench/synth_pdf/debug/reproduce_error.py
pdf_parse_bench/utilities/__init__.py
pdf_parse_bench/utilities/base_parser.py
pdf_parse_bench/utilities/data.py
pdf_parse_bench/utilities/formula_renderer.py
pdf_parse_bench/utilities/formula_viewer.py
pdf_parse_bench/utilities/generate_benchmark_table.py
pdf_parse_bench/utilities/vlm_prompt.py
pdf_parse_bench/data/2025-10-v1/ground_truth/000.json
pdf_parse_bench/data/2025-10-v1/ground_truth/001.json
pdf_parse_bench/data/2025-10-v1/ground_truth/002.json
pdf_parse_bench/data/2025-10-v1/ground_truth/003.json
pdf_parse_bench/data/2025-10-v1/ground_truth/004.json
pdf_parse_bench/data/2025-10-v1/ground_truth/005.json
pdf_parse_bench/data/2025-10-v1/ground_truth/006.json
pdf_parse_bench/data/2025-10-v1/ground_truth/007.json
pdf_parse_bench/data/2025-10-v1/ground_truth/008.json
pdf_parse_bench/data/2025-10-v1/ground_truth/009.json
pdf_parse_bench/data/2025-10-v1/ground_truth/010.json
pdf_parse_bench/data/2025-10-v1/ground_truth/011.json
pdf_parse_bench/data/2025-10-v1/ground_truth/012.json
pdf_parse_bench/data/2025-10-v1/ground_truth/013.json
pdf_parse_bench/data/2025-10-v1/ground_truth/014.json
pdf_parse_bench/data/2025-10-v1/ground_truth/015.json
pdf_parse_bench/data/2025-10-v1/ground_truth/016.json
pdf_parse_bench/data/2025-10-v1/ground_truth/017.json
pdf_parse_bench/data/2025-10-v1/ground_truth/018.json
pdf_parse_bench/data/2025-10-v1/ground_truth/019.json
pdf_parse_bench/data/2025-10-v1/ground_truth/020.json
pdf_parse_bench-0.3.0.dist-info/METADATA
pdf_parse_bench-0.3.0.dist-info/WHEEL
pdf_parse_bench-0.3.0.dist-info/licenses/LICENSE
pdf_parse_bench-0.3.0.dist-info/RECORD
