Metadata-Version: 2.4
Name: pdf-parse-bench
Version: 0.3.0
Summary: Benchmark suite for evaluating PDF parser quality on mathematical formulas
Project-URL: Homepage, https://github.com/phorn1/pdf-parse-bench
Project-URL: Repository, https://github.com/phorn1/pdf-parse-bench
Project-URL: Issues, https://github.com/phorn1/pdf-parse-bench/issues
Author-email: Pius Horn <piushorn@me.com>
License: MIT License
License-File: LICENSE
Keywords: benchmark,evaluation,mathematical-formulas,ocr,parser,pdf
Classifier: Development Status :: 3 - Alpha
Classifier: Intended Audience :: Developers
Classifier: Intended Audience :: Science/Research
Classifier: License :: OSI Approved :: MIT License
Classifier: Operating System :: OS Independent
Classifier: Programming Language :: Python :: 3
Classifier: Programming Language :: Python :: 3.12
Classifier: Programming Language :: Python :: 3.13
Classifier: Topic :: Scientific/Engineering
Classifier: Topic :: Software Development :: Quality Assurance
Classifier: Topic :: Software Development :: Testing
Classifier: Topic :: Text Processing
Requires-Python: >=3.12
Requires-Dist: duckdb>=1.4.1
Requires-Dist: faker>=37.11.0
Requires-Dist: google-genai>=1.46.0
Requires-Dist: levenshtein>=0.27.1
Requires-Dist: mistralai>=1.9.0
Requires-Dist: nltk>=3.9.1
Requires-Dist: notebook>=7.5.0
Requires-Dist: openai>=1.99.0
Requires-Dist: pillow>=10.0.0
Requires-Dist: pydantic-settings>=2.0.0
Requires-Dist: pydantic>=2.10
Requires-Dist: pylatexenc>=2.10
Requires-Dist: pymupdf>=1.24.0
Requires-Dist: python-dotenv>=1.0.0
Requires-Dist: pyyaml>=6.0.0
Requires-Dist: requests>=2.32.0
Requires-Dist: rich>=14.1.0
Requires-Dist: tqdm>=4.66.0
